asyncgTTS/__init__.py
asyncgTTS/_decos.py
asyncgTTS/asyncgTTS.py
asyncgTTS/config.py
asyncgTTS/errors.py
asyncgTTS/token.py
async_gTTS-0.3.0.dist-info/LICENCE
async_gTTS-0.3.0.dist-info/METADATA
async_gTTS-0.3.0.dist-info/WHEEL
async_gTTS-0.3.0.dist-info/top_level.txt
async_gTTS-0.3.0.dist-info/RECORD
