Metadata-Version: 2.1
Name: async-gTTS
Version: 0.3.0
Summary: Async interfaces to the official Google Text to Speech API.
Home-page: https://github.com/regulad/async-gTTS
Author: regulad
Author-email: regulad@outlook.com
License: MIT
Download-URL: https://github.com/regulad/async-gTTS/archive/refs/heads/master.zip
Keywords: async,TTS,gtts,text to speech
Platform: UNKNOWN
Classifier: Intended Audience :: Developers
Classifier: License :: OSI Approved :: MIT License
Classifier: Programming Language :: Python :: 3
Classifier: Programming Language :: Python :: 3.6
Classifier: Programming Language :: Python :: 3.7
Classifier: Programming Language :: Python :: 3.8
Classifier: Programming Language :: Python :: 3.9
License-File: LICENCE
Requires-Dist: aiohttp
Requires-Dist: pyJWT[crypto]
